sdinterp/__init__.py
sdinterp/interpolator.py
sdinterp/interpolation/__init__.py
sdinterp/interpolation/idw.py
sdinterp/interpolation/linear.py
sdinterp/interpolation/nearest.py
sdinterp/interpolation/rbf.py
sdinterp/interpolation/kriging/__init__.py
sdinterp/interpolation/kriging/ordinary.py
sdinterp/interpolation/kriging/simple.py
sdinterp/interpolation/kriging/universal.py
sdinterp/variogram/__init__.py
sdinterp/variogram/empirical.py
sdinterp/variogram/models.py
sdinterp-0.0.1.dist-info/LICENSE
sdinterp-0.0.1.dist-info/METADATA
sdinterp-0.0.1.dist-info/WHEEL
sdinterp-0.0.1.dist-info/top_level.txt
sdinterp-0.0.1.dist-info/RECORD
