Metadata-Version: 2.1
Name: sdinterp
Version: 0.0.1
Summary: A package providing single interface to different interpolation methods
Author-email: Aleksandr Popov <popov.aleksandr.v01@gmail.com>
License: MIT
Project-URL: Homepage, https://github.com/rytuo/sdinterp
Classifier: Programming Language :: Python :: 3
Classifier: License :: OSI Approved :: MIT License
Classifier: Operating System :: OS Independent
Requires-Python: >=3.9
License-File: LICENSE
Requires-Dist: gstools (>=1.4.1)
Requires-Dist: numpy (>=1.23.5)
Requires-Dist: scipy (>=1.10.0)
